holy_diver/__init__.py
holy_diver/config.py
holy_diver/config_list.py
holy_diver/config_mixin.py
holy_diver/constants.py
holy_diver-0.1.0a3.dist-info/AUTHORS.rst
holy_diver-0.1.0a3.dist-info/LICENSE
holy_diver-0.1.0a3.dist-info/METADATA
holy_diver-0.1.0a3.dist-info/WHEEL
holy_diver-0.1.0a3.dist-info/top_level.txt
holy_diver-0.1.0a3.dist-info/RECORD
