Metadata-Version: 2.1
Name: holy-diver
Version: 0.1.0a3
Summary: A dot-accessible configuration manager for deeply nested configuration files.
Home-page: https://github.com/ndgigliotti/holy-diver
Download-URL: https://github.com/ndgigliotti/holy-diver/archive/refs/tags/v0.1.0-alpha.3.tar.gz
Author: Nick Gigliotti
Author-email: ndgigliotti@gmail.com
License: MIT license
Keywords: holy_diver,holy-diver,dot config,config,configuration,config file,configuration file,configuration manager,config manager,configuration management,yaml,json,dot accessible,dot-accessible,attribute,attribute accessible,attribute-accessible,recursive,nested,nested configuration,nested config,deeply nested
Classifier: Development Status :: 2 - Pre-Alpha
Classifier: Intended Audience :: Developers
Classifier: License :: OSI Approved :: MIT License
Classifier: Natural Language :: English
Classifier: Programming Language :: Python :: 3
Classifier: Programming Language :: Python :: 3.9
Classifier: Programming Language :: Python :: 3.10
Requires-Python: >=3.9
License-File: LICENSE
License-File: AUTHORS.rst
